devtools_character_map/__init__.py
devtools_character_map-1.0.1.dist-info/METADATA
devtools_character_map-1.0.1.dist-info/WHEEL
devtools_character_map-1.0.1.dist-info/top_level.txt
devtools_character_map-1.0.1.dist-info/RECORD
