Metadata-Version: 2.1
Name: devtools-character-map
Version: 1.0.1
Summary: Character map and Unicode lookup
Home-page: https://devtools.at/tools/character-map
Author: DevTools.at
Author-email: hello@devtools.at
Project-URL: Homepage, https://devtools.at/tools/character-map
Project-URL: Repository, https://github.com/devtools-at/character-map
Classifier: Development Status :: 4 - Beta
Classifier: Intended Audience :: Developers
Classifier: License :: OSI Approved :: MIT License
Classifier: Programming Language :: Python :: 3
Requires-Python: >=3.8
